migrations/__init__.py
amount_field-0.1.0.dist-info/METADATA
amount_field-0.1.0.dist-info/WHEEL
amount_field-0.1.0.dist-info/top_level.txt
amount_field-0.1.0.dist-info/RECORD
