Metadata-Version: 2.1
Name: amount-field
Version: 0.1.0
Summary: A Django app for handling amounts, currencies, and prices
Home-page: https://github.com/SyedMaazHassan/amount_field
Author: Syed Maaz Hassan
Author-email: hafizmaazhassan33@gmail.com
License: UNKNOWN
Platform: UNKNOWN
Classifier: Programming Language :: Python :: 3
Classifier: License :: OSI Approved :: MIT License
Classifier: Operating System :: OS Independent
Requires-Dist: Django
